pretix_roomsharing/__init__.py
pretix_roomsharing/checkoutflow.py
pretix_roomsharing/forms.py
pretix_roomsharing/models.py
pretix_roomsharing/signals.py
pretix_roomsharing/tasks.py
pretix_roomsharing/urls.py
pretix_roomsharing/views.py
pretix_roomsharing/locale/de/LC_MESSAGES/django.mo
pretix_roomsharing/locale/de/LC_MESSAGES/django.po
pretix_roomsharing/locale/de_Informal/.gitkeep
pretix_roomsharing/locale/de_Informal/LC_MESSAGES/django.mo
pretix_roomsharing/locale/de_Informal/LC_MESSAGES/django.po
pretix_roomsharing/migrations/0001_initial.py
pretix_roomsharing/migrations/__init__.py
pretix_roomsharing/static/pretix_roomsharing/.gitkeep
pretix_roomsharing/templates/pretix_roomsharing/.gitkeep
pretix_roomsharing/templates/pretix_roomsharing/checkout_confirm.html
pretix_roomsharing/templates/pretix_roomsharing/checkout_room.html
pretix_roomsharing/templates/pretix_roomsharing/control_delete.html
pretix_roomsharing/templates/pretix_roomsharing/control_detail.html
pretix_roomsharing/templates/pretix_roomsharing/control_list.html
pretix_roomsharing/templates/pretix_roomsharing/control_order_info.html
pretix_roomsharing/templates/pretix_roomsharing/control_order_room_change.html
pretix_roomsharing/templates/pretix_roomsharing/control_stats.html
pretix_roomsharing/templates/pretix_roomsharing/fragment_roomform.html
pretix_roomsharing/templates/pretix_roomsharing/order_info.html
pretix_roomsharing/templates/pretix_roomsharing/order_room_change.html
pretix_roomsharing/templates/pretix_roomsharing/settings.html
pretix_roomsharing/templates/pretix_roomsharing/user_roomsharing.html
pretix_roomsharing/templatetags/__init__.py
pretix_roomsharing/templatetags/room_tags.py
pretix_roomsharing-0.1.0.dist-info/LICENSE
pretix_roomsharing-0.1.0.dist-info/METADATA
pretix_roomsharing-0.1.0.dist-info/WHEEL
pretix_roomsharing-0.1.0.dist-info/entry_points.txt
pretix_roomsharing-0.1.0.dist-info/top_level.txt
pretix_roomsharing-0.1.0.dist-info/RECORD
