Metadata-Version: 2.1
Name: pretix-roomsharing
Version: 0.1.0
Summary: Pretix roomsharing allows attendees to setup with which people they'd like to share a room
Home-page: https://github.com/Techwolf12/pretix-roomsharing
Author: Christiaan de Die le Clercq (techwolf12)
Author-email: contact@techwolf12.nl
License: Apache
License-File: LICENSE
